cuffers/__init__.py
cuffers/__main__.py
cuffers/main.py
cuffers-0.0.2.dist-info/LICENSE
cuffers-0.0.2.dist-info/METADATA
cuffers-0.0.2.dist-info/WHEEL
cuffers-0.0.2.dist-info/top_level.txt
cuffers-0.0.2.dist-info/RECORD
