Metadata-Version: 2.1
Name: cuffers
Version: 0.0.2
Summary: a python module to split a large file into smaller files with multiple processes.
Author-email: GGN_2015 <premierbob@qq.com>
License: MIT License
Requires-Python: >=3.11
License-File: LICENSE
Requires-Dist: tqdm
